<?xml version="1.0" encoding="utf-8"?>
<GrhDatas>
  <Stationary>
    <Count>193</Count>
    <Item0>
      <Index>152</Index>
      <Categorization>Background.desert</Categorization>
      <AutomaticSize>True</AutomaticSize>
      <Texture>
        <Name>Grh/Background/desert</Name>
        <Source>0,0,640,224</Source>
      </Texture>
    </Item0>
    <Item1>
      <Index>137</Index>
      <Categorization>Background.sky</Categorization>
      <AutomaticSize>True</AutomaticSize>
      <Texture>
        <Name>Grh/Background/sky</Name>
        <Source>0,0,1024,238</Source>
      </Texture>
    </Item1>
    <Item2>
      <Index>138</Index>
      <Categorization>Background.trees.dense</Categorization>
      <AutomaticSize>True</AutomaticSize>
      <Texture>
        <Name>Grh/Background/trees/dense</Name>
        <Source>0,0,1024,512</Source>
      </Texture>
    </Item2>
    <Item3>
      <Index>139</Index>
      <Categorization>Background.trees.sparse</Categorization>
      <AutomaticSize>True</AutomaticSize>
      <Texture>
        <Name>Grh/Background/trees/sparse</Name>
        <Source>0,0,1024,512</Source>
      </Texture>
    </Item3>
    <Item4>
      <Index>86</Index>
      <Categorization>Character.Crystal.ArmLower</Categorization>
      <AutomaticSize>True</AutomaticSize>
      <Texture>
        <Name>Grh/Character/Crystal/ArmLower</Name>
        <Source>0,0,6,20</Source>
      </Texture>
    </Item4>
    <Item5>
      <Index>87</Index>
      <Categorization>Character.Crystal.ArmUpper</Categorization>
      <AutomaticSize>True</AutomaticSize>
      <Texture>
        <Name>Grh/Character/Crystal/ArmUpper</Name>
        <Source>0,0,6,12</Source>
      </Texture>
    </Item5>
    <Item6>
      <Index>88</Index>
      <Categorization>Character.Crystal.Head</Categorization>
      <AutomaticSize>True</AutomaticSize>
      <Texture>
        <Name>Grh/Character/Crystal/Head</Name>
        <Source>0,0,19,20</Source>
      </Texture>
    </Item6>
    <Item7>
      <Index>89</Index>
      <Categorization>Character.Crystal.LegLower</Categorization>
      <AutomaticSize>True</AutomaticSize>
      <Texture>
        <Name>Grh/Character/Crystal/LegLower</Name>
        <Source>0,0,13,19</Source>
      </Texture>
    </Item7>
    <Item8>
      <Index>90</Index>
      <Categorization>Character.Crystal.LegUpper</Categorization>
      <AutomaticSize>True</AutomaticSize>
      <Texture>
        <Name>Grh/Character/Crystal/LegUpper</Name>
        <Source>0,0,12,22</Source>
      </Texture>
    </Item8>
    <Item9>
      <Index>91</Index>
      <Categorization>Character.Crystal.Neck</Categorization>
      <AutomaticSize>True</AutomaticSize>
      <Texture>
        <Name>Grh/Character/Crystal/Neck</Name>
        <Source>0,0,5,9</Source>
      </Texture>
    </Item9>
    <Item10>
      <Index>92</Index>
      <Categorization>Character.Crystal.Shoe</Categorization>
      <AutomaticSize>True</AutomaticSize>
      <Texture>
        <Name>Grh/Character/Crystal/Shoe</Name>
        <Source>0,0,6,18</Source>
      </Texture>
    </Item10>
    <Item11>
      <Index>93</Index>
      <Categorization>Character.Crystal.Torso</Categorization>
      <AutomaticSize>True</AutomaticSize>
      <Texture>
        <Name>Grh/Character/Crystal/Torso</Name>
        <Source>0,0,14,28</Source>
      </Texture>
    </Item11>
    <Item12>
      <Index>78</Index>
      <Categorization>Character.Naked.ArmLower</Categorization>
      <AutomaticSize>True</AutomaticSize>
      <Texture>
        <Name>Grh/Character/Naked/ArmLower</Name>
        <Source>0,0,6,20</Source>
      </Texture>
    </Item12>
    <Item13>
      <Index>79</Index>
      <Categorization>Character.Naked.ArmUpper</Categorization>
      <AutomaticSize>True</AutomaticSize>
      <Texture>
        <Name>Grh/Character/Naked/ArmUpper</Name>
        <Source>0,0,6,12</Source>
      </Texture>
    </Item13>
    <Item14>
      <Index>80</Index>
      <Categorization>Character.Naked.Head</Categorization>
      <AutomaticSize>True</AutomaticSize>
      <Texture>
        <Name>Grh/Character/Naked/Head</Name>
        <Source>0,0,19,19</Source>
      </Texture>
    </Item14>
    <Item15>
      <Index>81</Index>
      <Categorization>Character.Naked.LegLower</Categorization>
      <AutomaticSize>True</AutomaticSize>
      <Texture>
        <Name>Grh/Character/Naked/LegLower</Name>
        <Source>0,0,13,19</Source>
      </Texture>
    </Item15>
    <Item16>
      <Index>82</Index>
      <Categorization>Character.Naked.LegUpper</Categorization>
      <AutomaticSize>True</AutomaticSize>
      <Texture>
        <Name>Grh/Character/Naked/LegUpper</Name>
        <Source>0,0,12,22</Source>
      </Texture>
    </Item16>
    <Item17>
      <Index>83</Index>
      <Categorization>Character.Naked.Neck</Categorization>
      <AutomaticSize>True</AutomaticSize>
      <Texture>
        <Name>Grh/Character/Naked/Neck</Name>
        <Source>0,0,5,9</Source>
      </Texture>
    </Item17>
    <Item18>
      <Index>84</Index>
      <Categorization>Character.Naked.Shoe</Categorization>
      <AutomaticSize>True</AutomaticSize>
      <Texture>
        <Name>Grh/Character/Naked/Shoe</Name>
        <Source>0,0,6,16</Source>
      </Texture>
    </Item18>
    <Item19>
      <Index>85</Index>
      <Categorization>Character.Naked.Torso</Categorization>
      <AutomaticSize>True</AutomaticSize>
      <Texture>
        <Name>Grh/Character/Naked/Torso</Name>
        <Source>0,0,14,28</Source>
      </Texture>
    </Item19>
    <Item20>
      <Index>178</Index>
      <Categorization>Character.Top Down.Basic.Down</Categorization>
      <AutomaticSize>True</AutomaticSize>
      <Texture>
        <Name>Grh/Character/Top Down/Basic/Down</Name>
        <Source>0,0,44,54</Source>
      </Texture>
    </Item20>
    <Item21>
      <Index>179</Index>
      <Categorization>Character.Top Down.Basic.Left</Categorization>
      <AutomaticSize>True</AutomaticSize>
      <Texture>
        <Name>Grh/Character/Top Down/Basic/Left</Name>
        <Source>0,0,44,54</Source>
      </Texture>
    </Item21>
    <Item22>
      <Index>180</Index>
      <Categorization>Character.Top Down.Basic.Right</Categorization>
      <AutomaticSize>True</AutomaticSize>
      <Texture>
        <Name>Grh/Character/Top Down/Basic/Right</Name>
        <Source>0,0,44,54</Source>
      </Texture>
    </Item22>
    <Item23>
      <Index>181</Index>
      <Categorization>Character.Top Down.Basic.Up</Categorization>
      <AutomaticSize>True</AutomaticSize>
      <Texture>
        <Name>Grh/Character/Top Down/Basic/Up</Name>
        <Source>0,0,44,54</Source>
      </Texture>
    </Item23>
    <Item24>
      <Index>158</Index>
      <Categorization>Character.Top Down.Crystal.Down</Categorization>
      <AutomaticSize>True</AutomaticSize>
      <Texture>
        <Name>Grh/Character/Top Down/Crystal/Down</Name>
        <Source>0,0,44,54</Source>
      </Texture>
    </Item24>
    <Item25>
      <Index>159</Index>
      <Categorization>Character.Top Down.Crystal.Left</Categorization>
      <AutomaticSize>True</AutomaticSize>
      <Texture>
        <Name>Grh/Character/Top Down/Crystal/Left</Name>
        <Source>0,0,44,54</Source>
      </Texture>
    </Item25>
    <Item26>
      <Index>160</Index>
      <Categorization>Character.Top Down.Crystal.Right</Categorization>
      <AutomaticSize>True</AutomaticSize>
      <Texture>
        <Name>Grh/Character/Top Down/Crystal/Right</Name>
        <Source>0,0,44,54</Source>
      </Texture>
    </Item26>
    <Item27>
      <Index>161</Index>
      <Categorization>Character.Top Down.Crystal.Up</Categorization>
      <AutomaticSize>True</AutomaticSize>
      <Texture>
        <Name>Grh/Character/Top Down/Crystal/Up</Name>
        <Source>0,0,44,54</Source>
      </Texture>
    </Item27>
    <Item28>
      <Index>104</Index>
      <Categorization>Character.Top Down.Zombie.Down</Categorization>
      <AutomaticSize>True</AutomaticSize>
      <Texture>
        <Name>Grh/Character/Top Down/Zombie/Down</Name>
        <Source>0,0,44,54</Source>
      </Texture>
    </Item28>
    <Item29>
      <Index>111</Index>
      <Categorization>Character.Top Down.Zombie.Left</Categorization>
      <AutomaticSize>True</AutomaticSize>
      <Texture>
        <Name>Grh/Character/Top Down/Zombie/Left</Name>
        <Source>0,0,44,54</Source>
      </Texture>
    </Item29>
    <Item30>
      <Index>112</Index>
      <Categorization>Character.Top Down.Zombie.Right</Categorization>
      <AutomaticSize>True</AutomaticSize>
      <Texture>
        <Name>Grh/Character/Top Down/Zombie/Right</Name>
        <Source>0,0,44,54</Source>
      </Texture>
    </Item30>
    <Item31>
      <Index>113</Index>
      <Categorization>Character.Top Down.Zombie.Up</Categorization>
      <AutomaticSize>True</AutomaticSize>
      <Texture>
        <Name>Grh/Character/Top Down/Zombie/Up</Name>
        <Source>0,0,44,54</Source>
      </Texture>
    </Item31>
    <Item32>
      <Index>204</Index>
      <Categorization>Character.Zombie.ArmLower</Categorization>
      <AutomaticSize>True</AutomaticSize>
      <Texture>
        <Name>Grh/Character/Zombie/ArmLower</Name>
        <Source>0,0,5,21</Source>
      </Texture>
    </Item32>
    <Item33>
      <Index>203</Index>
      <Categorization>Character.Zombie.ArmUpper</Categorization>
      <AutomaticSize>True</AutomaticSize>
      <Texture>
        <Name>Grh/Character/Zombie/ArmUpper</Name>
        <Source>0,0,6,10</Source>
      </Texture>
    </Item33>
    <Item34>
      <Index>200</Index>
      <Categorization>Character.Zombie.Head</Categorization>
      <AutomaticSize>True</AutomaticSize>
      <Texture>
        <Name>Grh/Character/Zombie/Head</Name>
        <Source>0,0,19,19</Source>
      </Texture>
    </Item34>
    <Item35>
      <Index>206</Index>
      <Categorization>Character.Zombie.LegLower</Categorization>
      <AutomaticSize>True</AutomaticSize>
      <Texture>
        <Name>Grh/Character/Zombie/LegLower</Name>
        <Source>0,0,13,19</Source>
      </Texture>
    </Item35>
    <Item36>
      <Index>205</Index>
      <Categorization>Character.Zombie.LegUpper</Categorization>
      <AutomaticSize>True</AutomaticSize>
      <Texture>
        <Name>Grh/Character/Zombie/LegUpper</Name>
        <Source>0,0,12,22</Source>
      </Texture>
    </Item36>
    <Item37>
      <Index>201</Index>
      <Categorization>Character.Zombie.Neck</Categorization>
      <AutomaticSize>True</AutomaticSize>
      <Texture>
        <Name>Grh/Character/Zombie/Neck</Name>
        <Source>0,0,5,9</Source>
      </Texture>
    </Item37>
    <Item38>
      <Index>207</Index>
      <Categorization>Character.Zombie.Shoe</Categorization>
      <AutomaticSize>True</AutomaticSize>
      <Texture>
        <Name>Grh/Character/Zombie/Shoe</Name>
        <Source>0,0,6,17</Source>
      </Texture>
    </Item38>
    <Item39>
      <Index>202</Index>
      <Categorization>Character.Zombie.Torso</Categorization>
      <AutomaticSize>True</AutomaticSize>
      <Texture>
        <Name>Grh/Character/Zombie/Torso</Name>
        <Source>0,0,16,28</Source>
      </Texture>
    </Item39>
    <Item40>
      <Index>176</Index>
      <Categorization>Effect.light</Categorization>
      <AutomaticSize>True</AutomaticSize>
      <Texture>
        <Name>Grh/Effect/light</Name>
        <Source>0,0,512,512</Source>
      </Texture>
    </Item40>
    <Item41>
      <Index>101</Index>
      <Categorization>GUI.addstat</Categorization>
      <AutomaticSize>True</AutomaticSize>
      <Texture>
        <Name>Grh/GUI/addstat</Name>
        <Source>0,0,12,12</Source>
      </Texture>
    </Item41>
    <Item42>
      <Index>31</Index>
      <Categorization>GUI.Default.Controls.Button.Background</Categorization>
      <AutomaticSize>True</AutomaticSize>
      <Texture>
        <Name>Grh/GUI/Default/Controls/Button/Background</Name>
        <Source>0,0,7,7</Source>
      </Texture>
    </Item42>
    <Item43>
      <Index>32</Index>
      <Categorization>GUI.Default.Controls.Button.Bottom</Categorization>
      <AutomaticSize>True</AutomaticSize>
      <Texture>
        <Name>Grh/GUI/Default/Controls/Button/Bottom</Name>
        <Source>0,0,7,5</Source>
      </Texture>
    </Item43>
    <Item44>
      <Index>33</Index>
      <Categorization>GUI.Default.Controls.Button.BottomLeft</Categorization>
      <AutomaticSize>True</AutomaticSize>
      <Texture>
        <Name>Grh/GUI/Default/Controls/Button/BottomLeft</Name>
        <Source>0,0,5,5</Source>
      </Texture>
    </Item44>
    <Item45>
      <Index>34</Index>
      <Categorization>GUI.Default.Controls.Button.BottomRight</Categorization>
      <AutomaticSize>True</AutomaticSize>
      <Texture>
        <Name>Grh/GUI/Default/Controls/Button/BottomRight</Name>
        <Source>0,0,5,5</Source>
      </Texture>
    </Item45>
    <Item46>
      <Index>35</Index>
      <Categorization>GUI.Default.Controls.Button.Left</Categorization>
      <AutomaticSize>True</AutomaticSize>
      <Texture>
        <Name>Grh/GUI/Default/Controls/Button/Left</Name>
        <Source>0,0,5,7</Source>
      </Texture>
    </Item46>
    <Item47>
      <Index>56</Index>
      <Categorization>GUI.Default.Controls.Button.MouseOver.Background</Categorization>
      <AutomaticSize>True</AutomaticSize>
      <Texture>
        <Name>Grh/GUI/Default/Controls/Button/MouseOver/Background</Name>
        <Source>0,0,7,7</Source>
      </Texture>
    </Item47>
    <Item48>
      <Index>48</Index>
      <Categorization>GUI.Default.Controls.Button.MouseOver.Bottom</Categorization>
      <AutomaticSize>True</AutomaticSize>
      <Texture>
        <Name>Grh/GUI/Default/Controls/Button/MouseOver/Bottom</Name>
        <Source>0,0,7,5</Source>
      </Texture>
    </Item48>
    <Item49>
      <Index>49</Index>
      <Categorization>GUI.Default.Controls.Button.MouseOver.BottomLeft</Categorization>
      <AutomaticSize>True</AutomaticSize>
      <Texture>
        <Name>Grh/GUI/Default/Controls/Button/MouseOver/BottomLeft</Name>
        <Source>0,0,5,5</Source>
      </Texture>
    </Item49>
    <Item50>
      <Index>50</Index>
      <Categorization>GUI.Default.Controls.Button.MouseOver.BottomRight</Categorization>
      <AutomaticSize>True</AutomaticSize>
      <Texture>
        <Name>Grh/GUI/Default/Controls/Button/MouseOver/BottomRight</Name>
        <Source>0,0,5,5</Source>
      </Texture>
    </Item50>
    <Item51>
      <Index>51</Index>
      <Categorization>GUI.Default.Controls.Button.MouseOver.Left</Categorization>
      <AutomaticSize>True</AutomaticSize>
      <Texture>
        <Name>Grh/GUI/Default/Controls/Button/MouseOver/Left</Name>
        <Source>0,0,5,7</Source>
      </Texture>
    </Item51>
    <Item52>
      <Index>52</Index>
      <Categorization>GUI.Default.Controls.Button.MouseOver.Right</Categorization>
      <AutomaticSize>True</AutomaticSize>
      <Texture>
        <Name>Grh/GUI/Default/Controls/Button/MouseOver/Right</Name>
        <Source>0,0,5,7</Source>
      </Texture>
    </Item52>
    <Item53>
      <Index>53</Index>
      <Categorization>GUI.Default.Controls.Button.MouseOver.Top</Categorization>
      <AutomaticSize>True</AutomaticSize>
      <Texture>
        <Name>Grh/GUI/Default/Controls/Button/MouseOver/Top</Name>
        <Source>0,0,7,5</Source>
      </Texture>
    </Item53>
    <Item54>
      <Index>57</Index>
      <Categorization>GUI.Default.Controls.Button.MouseOver.TopLeft</Categorization>
      <AutomaticSize>True</AutomaticSize>
      <Texture>
        <Name>Grh/GUI/Default/Controls/Button/MouseOver/TopLeft</Name>
        <Source>0,0,5,5</Source>
      </Texture>
    </Item54>
    <Item55>
      <Index>58</Index>
      <Categorization>GUI.Default.Controls.Button.MouseOver.TopRight</Categorization>
      <AutomaticSize>True</AutomaticSize>
      <Texture>
        <Name>Grh/GUI/Default/Controls/Button/MouseOver/TopRight</Name>
        <Source>0,0,5,5</Source>
      </Texture>
    </Item55>
    <Item56>
      <Index>55</Index>
      <Categorization>GUI.Default.Controls.Button.Pressed.Background</Categorization>
      <AutomaticSize>True</AutomaticSize>
      <Texture>
        <Name>Grh/GUI/Default/Controls/Button/Pressed/Background</Name>
        <Source>0,0,7,7</Source>
      </Texture>
    </Item56>
    <Item57>
      <Index>40</Index>
      <Categorization>GUI.Default.Controls.Button.Pressed.Bottom</Categorization>
      <AutomaticSize>True</AutomaticSize>
      <Texture>
        <Name>Grh/GUI/Default/Controls/Button/Pressed/Bottom</Name>
        <Source>0,0,7,5</Source>
      </Texture>
    </Item57>
    <Item58>
      <Index>41</Index>
      <Categorization>GUI.Default.Controls.Button.Pressed.BottomLeft</Categorization>
      <AutomaticSize>True</AutomaticSize>
      <Texture>
        <Name>Grh/GUI/Default/Controls/Button/Pressed/BottomLeft</Name>
        <Source>0,0,5,5</Source>
      </Texture>
    </Item58>
    <Item59>
      <Index>42</Index>
      <Categorization>GUI.Default.Controls.Button.Pressed.BottomRight</Categorization>
      <AutomaticSize>True</AutomaticSize>
      <Texture>
        <Name>Grh/GUI/Default/Controls/Button/Pressed/BottomRight</Name>
        <Source>0,0,5,5</Source>
      </Texture>
    </Item59>
    <Item60>
      <Index>43</Index>
      <Categorization>GUI.Default.Controls.Button.Pressed.Left</Categorization>
      <AutomaticSize>True</AutomaticSize>
      <Texture>
        <Name>Grh/GUI/Default/Controls/Button/Pressed/Left</Name>
        <Source>0,0,5,7</Source>
      </Texture>
    </Item60>
    <Item61>
      <Index>44</Index>
      <Categorization>GUI.Default.Controls.Button.Pressed.Right</Categorization>
      <AutomaticSize>True</AutomaticSize>
      <Texture>
        <Name>Grh/GUI/Default/Controls/Button/Pressed/Right</Name>
        <Source>0,0,5,7</Source>
      </Texture>
    </Item61>
    <Item62>
      <Index>45</Index>
      <Categorization>GUI.Default.Controls.Button.Pressed.Top</Categorization>
      <AutomaticSize>True</AutomaticSize>
      <Texture>
        <Name>Grh/GUI/Default/Controls/Button/Pressed/Top</Name>
        <Source>0,0,7,5</Source>
      </Texture>
    </Item62>
    <Item63>
      <Index>46</Index>
      <Categorization>GUI.Default.Controls.Button.Pressed.TopLeft</Categorization>
      <AutomaticSize>True</AutomaticSize>
      <Texture>
        <Name>Grh/GUI/Default/Controls/Button/Pressed/TopLeft</Name>
        <Source>0,0,5,5</Source>
      </Texture>
    </Item63>
    <Item64>
      <Index>47</Index>
      <Categorization>GUI.Default.Controls.Button.Pressed.TopRight</Categorization>
      <AutomaticSize>True</AutomaticSize>
      <Texture>
        <Name>Grh/GUI/Default/Controls/Button/Pressed/TopRight</Name>
        <Source>0,0,5,5</Source>
      </Texture>
    </Item64>
    <Item65>
      <Index>36</Index>
      <Categorization>GUI.Default.Controls.Button.Right</Categorization>
      <AutomaticSize>True</AutomaticSize>
      <Texture>
        <Name>Grh/GUI/Default/Controls/Button/Right</Name>
        <Source>0,0,5,7</Source>
      </Texture>
    </Item65>
    <Item66>
      <Index>37</Index>
      <Categorization>GUI.Default.Controls.Button.Top</Categorization>
      <AutomaticSize>True</AutomaticSize>
      <Texture>
        <Name>Grh/GUI/Default/Controls/Button/Top</Name>
        <Source>0,0,7,5</Source>
      </Texture>
    </Item66>
    <Item67>
      <Index>38</Index>
      <Categorization>GUI.Default.Controls.Button.TopLeft</Categorization>
      <AutomaticSize>True</AutomaticSize>
      <Texture>
        <Name>Grh/GUI/Default/Controls/Button/TopLeft</Name>
        <Source>0,0,5,5</Source>
      </Texture>
    </Item67>
    <Item68>
      <Index>39</Index>
      <Categorization>GUI.Default.Controls.Button.TopRight</Categorization>
      <AutomaticSize>True</AutomaticSize>
      <Texture>
        <Name>Grh/GUI/Default/Controls/Button/TopRight</Name>
        <Source>0,0,5,5</Source>
      </Texture>
    </Item68>
    <Item69>
      <Index>110</Index>
      <Categorization>GUI.Default.Controls.Chat Bubble.Background</Categorization>
      <AutomaticSize>True</AutomaticSize>
      <Texture>
        <Name>Grh/GUI/Default/Controls/Chat Bubble/Background</Name>
        <Source>0,0,5,5</Source>
      </Texture>
    </Item69>
    <Item70>
      <Index>60</Index>
      <Categorization>GUI.Default.Controls.Chat Bubble.Bottom</Categorization>
      <AutomaticSize>True</AutomaticSize>
      <Texture>
        <Name>Grh/GUI/Default/Controls/Chat Bubble/Bottom</Name>
        <Source>0,0,5,5</Source>
      </Texture>
    </Item70>
    <Item71>
      <Index>102</Index>
      <Categorization>GUI.Default.Controls.Chat Bubble.BottomLeft</Categorization>
      <AutomaticSize>True</AutomaticSize>
      <Texture>
        <Name>Grh/GUI/Default/Controls/Chat Bubble/BottomLeft</Name>
        <Source>0,0,5,5</Source>
      </Texture>
    </Item71>
    <Item72>
      <Index>103</Index>
      <Categorization>GUI.Default.Controls.Chat Bubble.BottomRight</Categorization>
      <AutomaticSize>True</AutomaticSize>
      <Texture>
        <Name>Grh/GUI/Default/Controls/Chat Bubble/BottomRight</Name>
        <Source>0,0,5,5</Source>
      </Texture>
    </Item72>
    <Item73>
      <Index>105</Index>
      <Categorization>GUI.Default.Controls.Chat Bubble.Left</Categorization>
      <AutomaticSize>True</AutomaticSize>
      <Texture>
        <Name>Grh/GUI/Default/Controls/Chat Bubble/Left</Name>
        <Source>0,0,5,5</Source>
      </Texture>
    </Item73>
    <Item74>
      <Index>106</Index>
      <Categorization>GUI.Default.Controls.Chat Bubble.Right</Categorization>
      <AutomaticSize>True</AutomaticSize>
      <Texture>
        <Name>Grh/GUI/Default/Controls/Chat Bubble/Right</Name>
        <Source>0,0,5,5</Source>
      </Texture>
    </Item74>
    <Item75>
      <Index>107</Index>
      <Categorization>GUI.Default.Controls.Chat Bubble.Top</Categorization>
      <AutomaticSize>True</AutomaticSize>
      <Texture>
        <Name>Grh/GUI/Default/Controls/Chat Bubble/Top</Name>
        <Source>0,0,5,5</Source>
      </Texture>
    </Item75>
    <Item76>
      <Index>108</Index>
      <Categorization>GUI.Default.Controls.Chat Bubble.TopLeft</Categorization>
      <AutomaticSize>True</AutomaticSize>
      <Texture>
        <Name>Grh/GUI/Default/Controls/Chat Bubble/TopLeft</Name>
        <Source>0,0,5,5</Source>
      </Texture>
    </Item76>
    <Item77>
      <Index>109</Index>
      <Categorization>GUI.Default.Controls.Chat Bubble.TopRight</Categorization>
      <AutomaticSize>True</AutomaticSize>
      <Texture>
        <Name>Grh/GUI/Default/Controls/Chat Bubble/TopRight</Name>
        <Source>0,0,5,5</Source>
      </Texture>
    </Item77>
    <Item78>
      <Index>25</Index>
      <Categorization>GUI.Default.Controls.CheckBox.Ticked</Categorization>
      <AutomaticSize>True</AutomaticSize>
      <Texture>
        <Name>Grh/GUI/Default/Controls/CheckBox/Ticked</Name>
        <Source>0,0,15,15</Source>
      </Texture>
    </Item78>
    <Item79>
      <Index>26</Index>
      <Categorization>GUI.Default.Controls.CheckBox.TickedMouseOver</Categorization>
      <AutomaticSize>True</AutomaticSize>
      <Texture>
        <Name>Grh/GUI/Default/Controls/CheckBox/TickedMouseOver</Name>
        <Source>0,0,15,15</Source>
      </Texture>
    </Item79>
    <Item80>
      <Index>27</Index>
      <Categorization>GUI.Default.Controls.CheckBox.TickedPressed</Categorization>
      <AutomaticSize>True</AutomaticSize>
      <Texture>
        <Name>Grh/GUI/Default/Controls/CheckBox/TickedPressed</Name>
        <Source>0,0,15,15</Source>
      </Texture>
    </Item80>
    <Item81>
      <Index>28</Index>
      <Categorization>GUI.Default.Controls.CheckBox.Unticked</Categorization>
      <AutomaticSize>True</AutomaticSize>
      <Texture>
        <Name>Grh/GUI/Default/Controls/CheckBox/Unticked</Name>
        <Source>0,0,15,15</Source>
      </Texture>
    </Item81>
    <Item82>
      <Index>29</Index>
      <Categorization>GUI.Default.Controls.CheckBox.UntickedMouseOver</Categorization>
      <AutomaticSize>True</AutomaticSize>
      <Texture>
        <Name>Grh/GUI/Default/Controls/CheckBox/UntickedMouseOver</Name>
        <Source>0,0,15,15</Source>
      </Texture>
    </Item82>
    <Item83>
      <Index>30</Index>
      <Categorization>GUI.Default.Controls.CheckBox.UntickedPressed</Categorization>
      <AutomaticSize>True</AutomaticSize>
      <Texture>
        <Name>Grh/GUI/Default/Controls/CheckBox/UntickedPressed</Name>
        <Source>0,0,15,15</Source>
      </Texture>
    </Item83>
    <Item84>
      <Index>16</Index>
      <Categorization>GUI.Default.Controls.Form.Background</Categorization>
      <AutomaticSize>True</AutomaticSize>
      <Texture>
        <Name>Grh/GUI/Default/Controls/Form/Background</Name>
        <Source>0,0,6,6</Source>
      </Texture>
    </Item84>
    <Item85>
      <Index>17</Index>
      <Categorization>GUI.Default.Controls.Form.Bottom</Categorization>
      <AutomaticSize>True</AutomaticSize>
      <Texture>
        <Name>Grh/GUI/Default/Controls/Form/Bottom</Name>
        <Source>0,0,6,6</Source>
      </Texture>
    </Item85>
    <Item86>
      <Index>18</Index>
      <Categorization>GUI.Default.Controls.Form.BottomLeft</Categorization>
      <AutomaticSize>True</AutomaticSize>
      <Texture>
        <Name>Grh/GUI/Default/Controls/Form/BottomLeft</Name>
        <Source>0,0,6,6</Source>
      </Texture>
    </Item86>
    <Item87>
      <Index>19</Index>
      <Categorization>GUI.Default.Controls.Form.BottomRight</Categorization>
      <AutomaticSize>True</AutomaticSize>
      <Texture>
        <Name>Grh/GUI/Default/Controls/Form/BottomRight</Name>
        <Source>0,0,6,6</Source>
      </Texture>
    </Item87>
    <Item88>
      <Index>61</Index>
      <Categorization>GUI.Default.Controls.Form.Buttons.Close</Categorization>
      <AutomaticSize>True</AutomaticSize>
      <Texture>
        <Name>Grh/GUI/Default/Controls/Form/Buttons/Close</Name>
        <Source>0,0,9,9</Source>
      </Texture>
    </Item88>
    <Item89>
      <Index>63</Index>
      <Categorization>GUI.Default.Controls.Form.Buttons.CloseMouseOver</Categorization>
      <AutomaticSize>True</AutomaticSize>
      <Texture>
        <Name>Grh/GUI/Default/Controls/Form/Buttons/CloseMouseOver</Name>
        <Source>0,0,9,9</Source>
      </Texture>
    </Item89>
    <Item90>
      <Index>64</Index>
      <Categorization>GUI.Default.Controls.Form.Buttons.ClosePressed</Categorization>
      <AutomaticSize>True</AutomaticSize>
      <Texture>
        <Name>Grh/GUI/Default/Controls/Form/Buttons/ClosePressed</Name>
        <Source>0,0,9,9</Source>
      </Texture>
    </Item90>
    <Item91>
      <Index>20</Index>
      <Categorization>GUI.Default.Controls.Form.Left</Categorization>
      <AutomaticSize>True</AutomaticSize>
      <Texture>
        <Name>Grh/GUI/Default/Controls/Form/Left</Name>
        <Source>0,0,6,6</Source>
      </Texture>
    </Item91>
    <Item92>
      <Index>21</Index>
      <Categorization>GUI.Default.Controls.Form.Right</Categorization>
      <AutomaticSize>True</AutomaticSize>
      <Texture>
        <Name>Grh/GUI/Default/Controls/Form/Right</Name>
        <Source>0,0,6,6</Source>
      </Texture>
    </Item92>
    <Item93>
      <Index>22</Index>
      <Categorization>GUI.Default.Controls.Form.Top</Categorization>
      <AutomaticSize>True</AutomaticSize>
      <Texture>
        <Name>Grh/GUI/Default/Controls/Form/Top</Name>
        <Source>0,0,6,22</Source>
      </Texture>
    </Item93>
    <Item94>
      <Index>23</Index>
      <Categorization>GUI.Default.Controls.Form.TopLeft</Categorization>
      <AutomaticSize>True</AutomaticSize>
      <Texture>
        <Name>Grh/GUI/Default/Controls/Form/TopLeft</Name>
        <Source>0,0,6,22</Source>
      </Texture>
    </Item94>
    <Item95>
      <Index>24</Index>
      <Categorization>GUI.Default.Controls.Form.TopRight</Categorization>
      <AutomaticSize>True</AutomaticSize>
      <Texture>
        <Name>Grh/GUI/Default/Controls/Form/TopRight</Name>
        <Source>0,0,6,22</Source>
      </Texture>
    </Item95>
    <Item96>
      <Index>153</Index>
      <Categorization>GUI.Default.Controls.ListBox.Background</Categorization>
      <AutomaticSize>True</AutomaticSize>
      <Texture>
        <Name>Grh/GUI/Default/Controls/ListBox/Background</Name>
        <Source>0,0,4,4</Source>
      </Texture>
    </Item96>
    <Item97>
      <Index>154</Index>
      <Categorization>GUI.Default.Controls.ListBox.Bottom</Categorization>
      <AutomaticSize>True</AutomaticSize>
      <Texture>
        <Name>Grh/GUI/Default/Controls/ListBox/Bottom</Name>
        <Source>0,0,4,4</Source>
      </Texture>
    </Item97>
    <Item98>
      <Index>155</Index>
      <Categorization>GUI.Default.Controls.ListBox.BottomLeft</Categorization>
      <AutomaticSize>True</AutomaticSize>
      <Texture>
        <Name>Grh/GUI/Default/Controls/ListBox/BottomLeft</Name>
        <Source>0,0,4,4</Source>
      </Texture>
    </Item98>
    <Item99>
      <Index>156</Index>
      <Categorization>GUI.Default.Controls.ListBox.BottomRight</Categorization>
      <AutomaticSize>True</AutomaticSize>
      <Texture>
        <Name>Grh/GUI/Default/Controls/ListBox/BottomRight</Name>
        <Source>0,0,4,4</Source>
      </Texture>
    </Item99>
    <Item100>
      <Index>157</Index>
      <Categorization>GUI.Default.Controls.ListBox.Center</Categorization>
      <AutomaticSize>True</AutomaticSize>
      <Texture>
        <Name>Grh/GUI/Default/Controls/ListBox/Center</Name>
        <Source>0,0,4,4</Source>
      </Texture>
    </Item100>
    <Item101>
      <Index>162</Index>
      <Categorization>GUI.Default.Controls.ListBox.Left</Categorization>
      <AutomaticSize>True</AutomaticSize>
      <Texture>
        <Name>Grh/GUI/Default/Controls/ListBox/Left</Name>
        <Source>0,0,4,4</Source>
      </Texture>
    </Item101>
    <Item102>
      <Index>163</Index>
      <Categorization>GUI.Default.Controls.ListBox.Right</Categorization>
      <AutomaticSize>True</AutomaticSize>
      <Texture>
        <Name>Grh/GUI/Default/Controls/ListBox/Right</Name>
        <Source>0,0,4,4</Source>
      </Texture>
    </Item102>
    <Item103>
      <Index>168</Index>
      <Categorization>GUI.Default.Controls.ListBox.Toolbar.First</Categorization>
      <AutomaticSize>True</AutomaticSize>
      <Texture>
        <Name>Grh/GUI/Default/Controls/ListBox/Toolbar/First</Name>
        <Source>0,0,9,7</Source>
      </Texture>
    </Item103>
    <Item104>
      <Index>172</Index>
      <Categorization>GUI.Default.Controls.ListBox.Toolbar.First_MouseOver</Categorization>
      <AutomaticSize>True</AutomaticSize>
      <Texture>
        <Name>Grh/GUI/Default/Controls/ListBox/Toolbar/First_MouseOver</Name>
        <Source>0,0,9,7</Source>
      </Texture>
    </Item104>
    <Item105>
      <Index>169</Index>
      <Categorization>GUI.Default.Controls.ListBox.Toolbar.Last</Categorization>
      <AutomaticSize>True</AutomaticSize>
      <Texture>
        <Name>Grh/GUI/Default/Controls/ListBox/Toolbar/Last</Name>
        <Source>0,0,9,7</Source>
      </Texture>
    </Item105>
    <Item106>
      <Index>173</Index>
      <Categorization>GUI.Default.Controls.ListBox.Toolbar.Last_MouseOver</Categorization>
      <AutomaticSize>True</AutomaticSize>
      <Texture>
        <Name>Grh/GUI/Default/Controls/ListBox/Toolbar/Last_MouseOver</Name>
        <Source>0,0,9,7</Source>
      </Texture>
    </Item106>
    <Item107>
      <Index>170</Index>
      <Categorization>GUI.Default.Controls.ListBox.Toolbar.Next</Categorization>
      <AutomaticSize>True</AutomaticSize>
      <Texture>
        <Name>Grh/GUI/Default/Controls/ListBox/Toolbar/Next</Name>
        <Source>0,0,9,7</Source>
      </Texture>
    </Item107>
    <Item108>
      <Index>174</Index>
      <Categorization>GUI.Default.Controls.ListBox.Toolbar.Next_MouseOver</Categorization>
      <AutomaticSize>True</AutomaticSize>
      <Texture>
        <Name>Grh/GUI/Default/Controls/ListBox/Toolbar/Next_MouseOver</Name>
        <Source>0,0,9,7</Source>
      </Texture>
    </Item108>
    <Item109>
      <Index>171</Index>
      <Categorization>GUI.Default.Controls.ListBox.Toolbar.Previous</Categorization>
      <AutomaticSize>True</AutomaticSize>
      <Texture>
        <Name>Grh/GUI/Default/Controls/ListBox/Toolbar/Previous</Name>
        <Source>0,0,9,7</Source>
      </Texture>
    </Item109>
    <Item110>
      <Index>175</Index>
      <Categorization>GUI.Default.Controls.ListBox.Toolbar.Previous_MouseOver</Categorization>
      <AutomaticSize>True</AutomaticSize>
      <Texture>
        <Name>Grh/GUI/Default/Controls/ListBox/Toolbar/Previous_MouseOver</Name>
        <Source>0,0,9,7</Source>
      </Texture>
    </Item110>
    <Item111>
      <Index>164</Index>
      <Categorization>GUI.Default.Controls.ListBox.Top</Categorization>
      <AutomaticSize>True</AutomaticSize>
      <Texture>
        <Name>Grh/GUI/Default/Controls/ListBox/Top</Name>
        <Source>0,0,4,4</Source>
      </Texture>
    </Item111>
    <Item112>
      <Index>165</Index>
      <Categorization>GUI.Default.Controls.ListBox.TopLeft</Categorization>
      <AutomaticSize>True</AutomaticSize>
      <Texture>
        <Name>Grh/GUI/Default/Controls/ListBox/TopLeft</Name>
        <Source>0,0,4,4</Source>
      </Texture>
    </Item112>
    <Item113>
      <Index>166</Index>
      <Categorization>GUI.Default.Controls.ListBox.TopRight</Categorization>
      <AutomaticSize>True</AutomaticSize>
      <Texture>
        <Name>Grh/GUI/Default/Controls/ListBox/TopRight</Name>
        <Source>0,0,4,4</Source>
      </Texture>
    </Item113>
    <Item114>
      <Index>126</Index>
      <Categorization>GUI.Default.Controls.SkillCastProgressBar.Background</Categorization>
      <AutomaticSize>True</AutomaticSize>
      <Texture>
        <Name>Grh/GUI/Default/Controls/SkillCastProgressBar/Background</Name>
        <Source>0,0,6,6</Source>
      </Texture>
    </Item114>
    <Item115>
      <Index>127</Index>
      <Categorization>GUI.Default.Controls.SkillCastProgressBar.Bottom</Categorization>
      <AutomaticSize>True</AutomaticSize>
      <Texture>
        <Name>Grh/GUI/Default/Controls/SkillCastProgressBar/Bottom</Name>
        <Source>0,0,6,6</Source>
      </Texture>
    </Item115>
    <Item116>
      <Index>128</Index>
      <Categorization>GUI.Default.Controls.SkillCastProgressBar.BottomLeft</Categorization>
      <AutomaticSize>True</AutomaticSize>
      <Texture>
        <Name>Grh/GUI/Default/Controls/SkillCastProgressBar/BottomLeft</Name>
        <Source>0,0,6,6</Source>
      </Texture>
    </Item116>
    <Item117>
      <Index>129</Index>
      <Categorization>GUI.Default.Controls.SkillCastProgressBar.BottomRight</Categorization>
      <AutomaticSize>True</AutomaticSize>
      <Texture>
        <Name>Grh/GUI/Default/Controls/SkillCastProgressBar/BottomRight</Name>
        <Source>0,0,6,6</Source>
      </Texture>
    </Item117>
    <Item118>
      <Index>130</Index>
      <Categorization>GUI.Default.Controls.SkillCastProgressBar.Left</Categorization>
      <AutomaticSize>True</AutomaticSize>
      <Texture>
        <Name>Grh/GUI/Default/Controls/SkillCastProgressBar/Left</Name>
        <Source>0,0,6,6</Source>
      </Texture>
    </Item118>
    <Item119>
      <Index>131</Index>
      <Categorization>GUI.Default.Controls.SkillCastProgressBar.Right</Categorization>
      <AutomaticSize>True</AutomaticSize>
      <Texture>
        <Name>Grh/GUI/Default/Controls/SkillCastProgressBar/Right</Name>
        <Source>0,0,6,6</Source>
      </Texture>
    </Item119>
    <Item120>
      <Index>132</Index>
      <Categorization>GUI.Default.Controls.SkillCastProgressBar.Top</Categorization>
      <AutomaticSize>True</AutomaticSize>
      <Texture>
        <Name>Grh/GUI/Default/Controls/SkillCastProgressBar/Top</Name>
        <Source>0,0,6,6</Source>
      </Texture>
    </Item120>
    <Item121>
      <Index>218</Index>
      <Categorization>GUI.Default.Controls.SkillCastProgressBar.TopLeft</Categorization>
      <AutomaticSize>True</AutomaticSize>
      <Texture>
        <Name>Grh/GUI/Default/Controls/SkillCastProgressBar/TopLeft</Name>
        <Source>0,0,6,6</Source>
      </Texture>
    </Item121>
    <Item122>
      <Index>219</Index>
      <Categorization>GUI.Default.Controls.SkillCastProgressBar.TopRight</Categorization>
      <AutomaticSize>True</AutomaticSize>
      <Texture>
        <Name>Grh/GUI/Default/Controls/SkillCastProgressBar/TopRight</Name>
        <Source>0,0,6,6</Source>
      </Texture>
    </Item122>
    <Item123>
      <Index>59</Index>
      <Categorization>GUI.Default.Controls.TextBox.Background</Categorization>
      <AutomaticSize>True</AutomaticSize>
      <Texture>
        <Name>Grh/GUI/Default/Controls/TextBox/Background</Name>
        <Source>0,0,4,4</Source>
      </Texture>
    </Item123>
    <Item124>
      <Index>8</Index>
      <Categorization>GUI.Default.Controls.TextBox.Bottom</Categorization>
      <AutomaticSize>True</AutomaticSize>
      <Texture>
        <Name>Grh/GUI/Default/Controls/TextBox/Bottom</Name>
        <Source>0,0,4,4</Source>
      </Texture>
    </Item124>
    <Item125>
      <Index>9</Index>
      <Categorization>GUI.Default.Controls.TextBox.BottomLeft</Categorization>
      <AutomaticSize>True</AutomaticSize>
      <Texture>
        <Name>Grh/GUI/Default/Controls/TextBox/BottomLeft</Name>
        <Source>0,0,4,4</Source>
      </Texture>
    </Item125>
    <Item126>
      <Index>10</Index>
      <Categorization>GUI.Default.Controls.TextBox.BottomRight</Categorization>
      <AutomaticSize>True</AutomaticSize>
      <Texture>
        <Name>Grh/GUI/Default/Controls/TextBox/BottomRight</Name>
        <Source>0,0,4,4</Source>
      </Texture>
    </Item126>
    <Item127>
      <Index>54</Index>
      <Categorization>GUI.Default.Controls.TextBox.Center</Categorization>
      <AutomaticSize>True</AutomaticSize>
      <Texture>
        <Name>Grh/GUI/Default/Controls/TextBox/Center</Name>
        <Source>0,0,4,4</Source>
      </Texture>
    </Item127>
    <Item128>
      <Index>11</Index>
      <Categorization>GUI.Default.Controls.TextBox.Left</Categorization>
      <AutomaticSize>True</AutomaticSize>
      <Texture>
        <Name>Grh/GUI/Default/Controls/TextBox/Left</Name>
        <Source>0,0,4,4</Source>
      </Texture>
    </Item128>
    <Item129>
      <Index>12</Index>
      <Categorization>GUI.Default.Controls.TextBox.Right</Categorization>
      <AutomaticSize>True</AutomaticSize>
      <Texture>
        <Name>Grh/GUI/Default/Controls/TextBox/Right</Name>
        <Source>0,0,4,4</Source>
      </Texture>
    </Item129>
    <Item130>
      <Index>13</Index>
      <Categorization>GUI.Default.Controls.TextBox.Top</Categorization>
      <AutomaticSize>True</AutomaticSize>
      <Texture>
        <Name>Grh/GUI/Default/Controls/TextBox/Top</Name>
        <Source>0,0,4,4</Source>
      </Texture>
    </Item130>
    <Item131>
      <Index>14</Index>
      <Categorization>GUI.Default.Controls.TextBox.TopLeft</Categorization>
      <AutomaticSize>True</AutomaticSize>
      <Texture>
        <Name>Grh/GUI/Default/Controls/TextBox/TopLeft</Name>
        <Source>0,0,4,4</Source>
      </Texture>
    </Item131>
    <Item132>
      <Index>15</Index>
      <Categorization>GUI.Default.Controls.TextBox.TopRight</Categorization>
      <AutomaticSize>True</AutomaticSize>
      <Texture>
        <Name>Grh/GUI/Default/Controls/TextBox/TopRight</Name>
        <Source>0,0,4,4</Source>
      </Texture>
    </Item132>
    <Item133>
      <Index>136</Index>
      <Categorization>GUI.Default.item_slot</Categorization>
      <AutomaticSize>True</AutomaticSize>
      <Texture>
        <Name>Grh/GUI/Default/item_slot</Name>
        <Source>0,0,32,32</Source>
      </Texture>
    </Item133>
    <Item134>
      <Index>143</Index>
      <Categorization>GUI.Default.status icon border</Categorization>
      <AutomaticSize>True</AutomaticSize>
      <Texture>
        <Name>Grh/GUI/Default/status icon border</Name>
        <Source>0,0,32,32</Source>
      </Texture>
    </Item134>
    <Item135>
      <Index>133</Index>
      <Categorization>GUI.Default.Toolbar.Equipped</Categorization>
      <AutomaticSize>True</AutomaticSize>
      <Texture>
        <Name>Grh/GUI/Default/Toolbar/Equipped</Name>
        <Source>0,0,32,32</Source>
      </Texture>
    </Item135>
    <Item136>
      <Index>167</Index>
      <Categorization>GUI.Default.Toolbar.Guild</Categorization>
      <AutomaticSize>True</AutomaticSize>
      <Texture>
        <Name>Grh/GUI/Default/Toolbar/Guild</Name>
        <Source>0,0,32,32</Source>
      </Texture>
    </Item136>
    <Item137>
      <Index>134</Index>
      <Categorization>GUI.Default.Toolbar.Inventory</Categorization>
      <AutomaticSize>True</AutomaticSize>
      <Texture>
        <Name>Grh/GUI/Default/Toolbar/Inventory</Name>
        <Source>0,0,32,32</Source>
      </Texture>
    </Item137>
    <Item138>
      <Index>135</Index>
      <Categorization>GUI.Default.Toolbar.Skills</Categorization>
      <AutomaticSize>True</AutomaticSize>
      <Texture>
        <Name>Grh/GUI/Default/Toolbar/Skills</Name>
        <Source>0,0,32,32</Source>
      </Texture>
    </Item138>
    <Item139>
      <Index>144</Index>
      <Categorization>GUI.Default.Toolbar.Stats</Categorization>
      <AutomaticSize>True</AutomaticSize>
      <Texture>
        <Name>Grh/GUI/Default/Toolbar/Stats</Name>
        <Source>0,0,32,32</Source>
      </Texture>
    </Item139>
    <Item140>
      <Index>100</Index>
      <Categorization>Item.Back.crystal</Categorization>
      <AutomaticSize>True</AutomaticSize>
      <Texture>
        <Name>Grh/Item/Back/crystal</Name>
        <Source>0,0,15,25</Source>
      </Texture>
    </Item140>
    <Item141>
      <Index>99</Index>
      <Categorization>Item.Body.crystal</Categorization>
      <AutomaticSize>True</AutomaticSize>
      <Texture>
        <Name>Grh/Item/Body/crystal</Name>
        <Source>0,0,22,22</Source>
      </Texture>
    </Item141>
    <Item142>
      <Index>98</Index>
      <Categorization>Item.Feet.crystal</Categorization>
      <AutomaticSize>True</AutomaticSize>
      <Texture>
        <Name>Grh/Item/Feet/crystal</Name>
        <Source>0,0,15,14</Source>
      </Texture>
    </Item142>
    <Item143>
      <Index>97</Index>
      <Categorization>Item.Head.crystal</Categorization>
      <AutomaticSize>True</AutomaticSize>
      <Texture>
        <Name>Grh/Item/Head/crystal</Name>
        <Source>0,0,11,16</Source>
      </Texture>
    </Item143>
    <Item144>
      <Index>96</Index>
      <Categorization>Item.Melee.titaniumsword</Categorization>
      <AutomaticSize>True</AutomaticSize>
      <Texture>
        <Name>Grh/Item/Melee/titaniumsword</Name>
        <Source>0,0,24,24</Source>
      </Texture>
    </Item144>
    <Item145>
      <Index>151</Index>
      <Categorization>Item.Misc.boombox</Categorization>
      <AutomaticSize>True</AutomaticSize>
      <Texture>
        <Name>Grh/Item/Misc/boombox</Name>
        <Source>0,0,70,37</Source>
      </Texture>
    </Item145>
    <Item146>
      <Index>94</Index>
      <Categorization>Item.Potion.blue</Categorization>
      <AutomaticSize>True</AutomaticSize>
      <Texture>
        <Name>Grh/Item/Potion/blue</Name>
        <Source>0,0,9,16</Source>
      </Texture>
    </Item146>
    <Item147>
      <Index>95</Index>
      <Categorization>Item.Potion.red</Categorization>
      <AutomaticSize>True</AutomaticSize>
      <Texture>
        <Name>Grh/Item/Potion/red</Name>
        <Source>0,0,9,16</Source>
      </Texture>
    </Item147>
    <Item148>
      <Index>177</Index>
      <Categorization>Item.Ranged.pistol</Categorization>
      <AutomaticSize>True</AutomaticSize>
      <Texture>
        <Name>Grh/Item/Ranged/pistol</Name>
        <Source>0,0,15,18</Source>
      </Texture>
    </Item148>
    <Item149>
      <Index>182</Index>
      <Categorization>Item.Ranged.rock</Categorization>
      <AutomaticSize>True</AutomaticSize>
      <Texture>
        <Name>Grh/Item/Ranged/rock</Name>
        <Source>0,0,11,9</Source>
      </Texture>
    </Item149>
    <Item150>
      <Index>114</Index>
      <Categorization>Map.Desert.doorway</Categorization>
      <AutomaticSize>True</AutomaticSize>
      <Texture>
        <Name>Grh/Map/Desert/doorway</Name>
        <Source>0,0,101,99</Source>
      </Texture>
    </Item150>
    <Item151>
      <Index>115</Index>
      <Categorization>Map.Desert.hill 1</Categorization>
      <AutomaticSize>True</AutomaticSize>
      <Texture>
        <Name>Grh/Map/Desert/hill 1</Name>
        <Source>0,0,97,64</Source>
      </Texture>
    </Item151>
    <Item152>
      <Index>116</Index>
      <Categorization>Map.Desert.hill 2</Categorization>
      <AutomaticSize>True</AutomaticSize>
      <Texture>
        <Name>Grh/Map/Desert/hill 2</Name>
        <Source>0,0,69,43</Source>
      </Texture>
    </Item152>
    <Item153>
      <Index>117</Index>
      <Categorization>Map.Desert.Platforms.01</Categorization>
      <AutomaticSize>True</AutomaticSize>
      <Texture>
        <Name>Grh/Map/Desert/Platforms/01</Name>
        <Source>0,0,93,47</Source>
      </Texture>
    </Item153>
    <Item154>
      <Index>118</Index>
      <Categorization>Map.Desert.Shrubbery.blue flower</Categorization>
      <AutomaticSize>True</AutomaticSize>
      <Texture>
        <Name>Grh/Map/Desert/Shrubbery/blue flower</Name>
        <Source>0,0,23,34</Source>
      </Texture>
    </Item154>
    <Item155>
      <Index>119</Index>
      <Categorization>Map.Desert.Shrubbery.cactus</Categorization>
      <AutomaticSize>True</AutomaticSize>
      <Texture>
        <Name>Grh/Map/Desert/Shrubbery/cactus</Name>
        <Source>0,0,40,65</Source>
      </Texture>
    </Item155>
    <Item156>
      <Index>120</Index>
      <Categorization>Map.Desert.Shrubbery.red flower</Categorization>
      <AutomaticSize>True</AutomaticSize>
      <Texture>
        <Name>Grh/Map/Desert/Shrubbery/red flower</Name>
        <Source>0,0,23,34</Source>
      </Texture>
    </Item156>
    <Item157>
      <Index>121</Index>
      <Categorization>Map.Desert.Shrubbery.shrub 01</Categorization>
      <AutomaticSize>True</AutomaticSize>
      <Texture>
        <Name>Grh/Map/Desert/Shrubbery/shrub 01</Name>
        <Source>0,0,24,23</Source>
      </Texture>
    </Item157>
    <Item158>
      <Index>122</Index>
      <Categorization>Map.Desert.Shrubbery.shrub 02</Categorization>
      <AutomaticSize>True</AutomaticSize>
      <Texture>
        <Name>Grh/Map/Desert/Shrubbery/shrub 02</Name>
        <Source>0,0,22,27</Source>
      </Texture>
    </Item158>
    <Item159>
      <Index>123</Index>
      <Categorization>Map.Desert.Shrubbery.shrub 03</Categorization>
      <AutomaticSize>True</AutomaticSize>
      <Texture>
        <Name>Grh/Map/Desert/Shrubbery/shrub 03</Name>
        <Source>0,0,13,16</Source>
      </Texture>
    </Item159>
    <Item160>
      <Index>124</Index>
      <Categorization>Map.Desert.Shrubbery.tree</Categorization>
      <AutomaticSize>True</AutomaticSize>
      <Texture>
        <Name>Grh/Map/Desert/Shrubbery/tree</Name>
        <Source>0,0,39,89</Source>
      </Texture>
    </Item160>
    <Item161>
      <Index>145</Index>
      <Categorization>Map.Desert.Tiled platform toppers.Grassy.Center.01</Categorization>
      <AutomaticSize>True</AutomaticSize>
      <Texture>
        <Name>Grh/Map/Desert/Tiled platform toppers/Grassy/Center/01</Name>
        <Source>0,0,32,21</Source>
      </Texture>
    </Item161>
    <Item162>
      <Index>146</Index>
      <Categorization>Map.Desert.Tiled platform toppers.Grassy.Left.01</Categorization>
      <AutomaticSize>True</AutomaticSize>
      <Texture>
        <Name>Grh/Map/Desert/Tiled platform toppers/Grassy/Left/01</Name>
        <Source>0,0,32,21</Source>
      </Texture>
    </Item162>
    <Item163>
      <Index>147</Index>
      <Categorization>Map.Desert.Tiled platform toppers.Grassy.Right.01</Categorization>
      <AutomaticSize>True</AutomaticSize>
      <Texture>
        <Name>Grh/Map/Desert/Tiled platform toppers/Grassy/Right/01</Name>
        <Source>0,0,32,21</Source>
      </Texture>
    </Item163>
    <Item164>
      <Index>148</Index>
      <Categorization>Map.Desert.Tiled platforms.Rocky.Center.01</Categorization>
      <AutomaticSize>True</AutomaticSize>
      <Texture>
        <Name>Grh/Map/Desert/Tiled platforms/Rocky/Center/01</Name>
        <Source>0,0,32,32</Source>
      </Texture>
    </Item164>
    <Item165>
      <Index>149</Index>
      <Categorization>Map.Desert.Tiled platforms.Rocky.Left.01</Categorization>
      <AutomaticSize>True</AutomaticSize>
      <Texture>
        <Name>Grh/Map/Desert/Tiled platforms/Rocky/Left/01</Name>
        <Source>0,0,32,32</Source>
      </Texture>
    </Item165>
    <Item166>
      <Index>150</Index>
      <Categorization>Map.Desert.Tiled platforms.Rocky.Right.01</Categorization>
      <AutomaticSize>True</AutomaticSize>
      <Texture>
        <Name>Grh/Map/Desert/Tiled platforms/Rocky/Right/01</Name>
        <Source>0,0,32,32</Source>
      </Texture>
    </Item166>
    <Item167>
      <Index>7</Index>
      <Categorization>Map.Platform.Grass.Bottom</Categorization>
      <AutomaticSize>True</AutomaticSize>
      <Texture>
        <Name>Grh/Map/Platform/Grass/Bottom</Name>
        <Source>0,0,32,1</Source>
      </Texture>
    </Item167>
    <Item168>
      <Index>4</Index>
      <Categorization>Map.Platform.Grass.Mid-Left</Categorization>
      <AutomaticSize>True</AutomaticSize>
      <Texture>
        <Name>Grh/Map/Platform/Grass/Mid-Left</Name>
        <Source>0,0,32,32</Source>
      </Texture>
    </Item168>
    <Item169>
      <Index>5</Index>
      <Categorization>Map.Platform.Grass.Mid-Mid</Categorization>
      <AutomaticSize>True</AutomaticSize>
      <Texture>
        <Name>Grh/Map/Platform/Grass/Mid-Mid</Name>
        <Source>0,0,32,32</Source>
      </Texture>
    </Item169>
    <Item170>
      <Index>6</Index>
      <Categorization>Map.Platform.Grass.Mid-Right</Categorization>
      <AutomaticSize>True</AutomaticSize>
      <Texture>
        <Name>Grh/Map/Platform/Grass/Mid-Right</Name>
        <Source>0,0,32,32</Source>
      </Texture>
    </Item170>
    <Item171>
      <Index>1</Index>
      <Categorization>Map.Platform.Grass.Top-Left</Categorization>
      <AutomaticSize>True</AutomaticSize>
      <Texture>
        <Name>Grh/Map/Platform/Grass/Top-Left</Name>
        <Source>0,0,32,32</Source>
      </Texture>
    </Item171>
    <Item172>
      <Index>2</Index>
      <Categorization>Map.Platform.Grass.Top-Mid</Categorization>
      <AutomaticSize>True</AutomaticSize>
      <Texture>
        <Name>Grh/Map/Platform/Grass/Top-Mid</Name>
        <Source>0,0,32,32</Source>
      </Texture>
    </Item172>
    <Item173>
      <Index>3</Index>
      <Categorization>Map.Platform.Grass.Top-Right</Categorization>
      <AutomaticSize>True</AutomaticSize>
      <Texture>
        <Name>Grh/Map/Platform/Grass/Top-Right</Name>
        <Source>0,0,32,32</Source>
      </Texture>
    </Item173>
    <Item174>
      <Index>66</Index>
      <Categorization>Particle.ankh</Categorization>
      <AutomaticSize>True</AutomaticSize>
      <Texture>
        <Name>Grh/Particle/ankh</Name>
        <Source>0,0,32,32</Source>
      </Texture>
    </Item174>
    <Item175>
      <Index>67</Index>
      <Categorization>Particle.ball</Categorization>
      <AutomaticSize>True</AutomaticSize>
      <Texture>
        <Name>Grh/Particle/ball</Name>
        <Source>0,0,32,32</Source>
      </Texture>
    </Item175>
    <Item176>
      <Index>68</Index>
      <Categorization>Particle.raindrop</Categorization>
      <AutomaticSize>True</AutomaticSize>
      <Texture>
        <Name>Grh/Particle/raindrop</Name>
        <Source>0,0,32,32</Source>
      </Texture>
    </Item176>
    <Item177>
      <Index>69</Index>
      <Categorization>Particle.shield</Categorization>
      <AutomaticSize>True</AutomaticSize>
      <Texture>
        <Name>Grh/Particle/shield</Name>
        <Source>0,0,32,32</Source>
      </Texture>
    </Item177>
    <Item178>
      <Index>70</Index>
      <Categorization>Particle.skull</Categorization>
      <AutomaticSize>True</AutomaticSize>
      <Texture>
        <Name>Grh/Particle/skull</Name>
        <Source>0,0,32,32</Source>
      </Texture>
    </Item178>
    <Item179>
      <Index>72</Index>
      <Categorization>Particle.snow</Categorization>
      <AutomaticSize>True</AutomaticSize>
      <Texture>
        <Name>Grh/Particle/snow</Name>
        <Source>0,0,32,32</Source>
      </Texture>
    </Item179>
    <Item180>
      <Index>71</Index>
      <Categorization>Particle.snow sharp</Categorization>
      <AutomaticSize>True</AutomaticSize>
      <Texture>
        <Name>Grh/Particle/snow sharp</Name>
        <Source>0,0,32,32</Source>
      </Texture>
    </Item180>
    <Item181>
      <Index>73</Index>
      <Categorization>Particle.sparkle</Categorization>
      <AutomaticSize>True</AutomaticSize>
      <Texture>
        <Name>Grh/Particle/sparkle</Name>
        <Source>0,0,32,32</Source>
      </Texture>
    </Item181>
    <Item182>
      <Index>74</Index>
      <Categorization>Particle.splatter</Categorization>
      <AutomaticSize>True</AutomaticSize>
      <Texture>
        <Name>Grh/Particle/splatter</Name>
        <Source>0,0,32,32</Source>
      </Texture>
    </Item182>
    <Item183>
      <Index>76</Index>
      <Categorization>Particle.star</Categorization>
      <AutomaticSize>True</AutomaticSize>
      <Texture>
        <Name>Grh/Particle/star</Name>
        <Source>0,0,32,32</Source>
      </Texture>
    </Item183>
    <Item184>
      <Index>75</Index>
      <Categorization>Particle.star sharp</Categorization>
      <AutomaticSize>True</AutomaticSize>
      <Texture>
        <Name>Grh/Particle/star sharp</Name>
        <Source>0,0,32,32</Source>
      </Texture>
    </Item184>
    <Item185>
      <Index>77</Index>
      <Categorization>Particle.sword</Categorization>
      <AutomaticSize>True</AutomaticSize>
      <Texture>
        <Name>Grh/Particle/sword</Name>
        <Source>0,0,32,32</Source>
      </Texture>
    </Item185>
    <Item186>
      <Index>183</Index>
      <Categorization>Quest.can start</Categorization>
      <AutomaticSize>True</AutomaticSize>
      <Texture>
        <Name>Grh/Quest/can start</Name>
        <Source>0,0,11,20</Source>
      </Texture>
    </Item186>
    <Item187>
      <Index>186</Index>
      <Categorization>Quest.cannot start</Categorization>
      <AutomaticSize>True</AutomaticSize>
      <Texture>
        <Name>Grh/Quest/cannot start</Name>
        <Source>0,0,11,20</Source>
      </Texture>
    </Item187>
    <Item188>
      <Index>184</Index>
      <Categorization>Quest.started</Categorization>
      <AutomaticSize>True</AutomaticSize>
      <Texture>
        <Name>Grh/Quest/started</Name>
        <Source>0,0,4,20</Source>
      </Texture>
    </Item188>
    <Item189>
      <Index>185</Index>
      <Categorization>Quest.turnin</Categorization>
      <AutomaticSize>True</AutomaticSize>
      <Texture>
        <Name>Grh/Quest/turnin</Name>
        <Source>0,0,4,20</Source>
      </Texture>
    </Item189>
    <Item190>
      <Index>140</Index>
      <Categorization>SkillIcon.heal</Categorization>
      <AutomaticSize>True</AutomaticSize>
      <Texture>
        <Name>Grh/SkillIcon/heal</Name>
        <Source>0,0,32,32</Source>
      </Texture>
    </Item190>
    <Item191>
      <Index>142</Index>
      <Categorization>SkillIcon.strengthen</Categorization>
      <AutomaticSize>True</AutomaticSize>
      <Texture>
        <Name>Grh/SkillIcon/strengthen</Name>
        <Source>0,0,32,32</Source>
      </Texture>
    </Item191>
    <Item192>
      <Index>141</Index>
      <Categorization>StatusIcon.strengthen</Categorization>
      <AutomaticSize>True</AutomaticSize>
      <Texture>
        <Name>Grh/StatusIcon/strengthen</Name>
        <Source>0,0,32,32</Source>
      </Texture>
    </Item192>
  </Stationary>
  <Animated>
    <Count>0</Count>
  </Animated>
  <AutomaticAnimated>
    <Count>20</Count>
    <Item0>
      <Index>214</Index>
      <Categorization>Character.Top Down.Basic.Walk Down</Categorization>
    </Item0>
    <Item1>
      <Index>215</Index>
      <Categorization>Character.Top Down.Basic.Walk Left</Categorization>
    </Item1>
    <Item2>
      <Index>216</Index>
      <Categorization>Character.Top Down.Basic.Walk Right</Categorization>
    </Item2>
    <Item3>
      <Index>217</Index>
      <Categorization>Character.Top Down.Basic.Walk Up</Categorization>
    </Item3>
    <Item4>
      <Index>210</Index>
      <Categorization>Character.Top Down.Crystal.Walk Down</Categorization>
    </Item4>
    <Item5>
      <Index>211</Index>
      <Categorization>Character.Top Down.Crystal.Walk Left</Categorization>
    </Item5>
    <Item6>
      <Index>212</Index>
      <Categorization>Character.Top Down.Crystal.Walk Right</Categorization>
    </Item6>
    <Item7>
      <Index>213</Index>
      <Categorization>Character.Top Down.Crystal.Walk Up</Categorization>
    </Item7>
    <Item8>
      <Index>198</Index>
      <Categorization>Character.Top Down.Zombie.Walk Down</Categorization>
    </Item8>
    <Item9>
      <Index>199</Index>
      <Categorization>Character.Top Down.Zombie.Walk Left</Categorization>
    </Item9>
    <Item10>
      <Index>208</Index>
      <Categorization>Character.Top Down.Zombie.Walk Right</Categorization>
    </Item10>
    <Item11>
      <Index>209</Index>
      <Categorization>Character.Top Down.Zombie.Walk Up</Categorization>
    </Item11>
    <Item12>
      <Index>125</Index>
      <Categorization>Effect.Teleport</Categorization>
    </Item12>
    <Item13>
      <Index>248</Index>
      <Categorization>Emoticons.Ellipsis</Categorization>
    </Item13>
    <Item14>
      <Index>249</Index>
      <Categorization>Emoticons.Exclamation</Categorization>
    </Item14>
    <Item15>
      <Index>250</Index>
      <Categorization>Emoticons.Heartbroken</Categorization>
    </Item15>
    <Item16>
      <Index>251</Index>
      <Categorization>Emoticons.Hearts</Categorization>
    </Item16>
    <Item17>
      <Index>252</Index>
      <Categorization>Emoticons.Meat</Categorization>
    </Item17>
    <Item18>
      <Index>253</Index>
      <Categorization>Emoticons.Question</Categorization>
    </Item18>
    <Item19>
      <Index>254</Index>
      <Categorization>Emoticons.Sweat</Categorization>
    </Item19>
  </AutomaticAnimated>
</GrhDatas>